[
  {
    "filename": "20260428_001027.jpg",
    "path": "/home/blueberry/code/my-window/20260428_001027.jpg",
    "size_bytes": 1282659,
    "modified": "2026-04-28 00:10:34"
  },
  {
    "filename": "20260427_215325.jpg",
    "path": "/home/blueberry/code/my-window/20260427_215325.jpg",
    "size_bytes": 1639150,
    "modified": "2026-04-27 21:53:32"
  },
  {
    "filename": "20260427_193607.jpg",
    "path": "/home/blueberry/code/my-window/20260427_193607.jpg",
    "size_bytes": 725801,
    "modified": "2026-04-27 19:36:13"
  },
  {
    "filename": "20260427_171901.jpg",
    "path": "/home/blueberry/code/my-window/20260427_171901.jpg",
    "size_bytes": 803080,
    "modified": "2026-04-27 17:19:08"
  },
  {
    "filename": "20260427_150137.jpg",
    "path": "/home/blueberry/code/my-window/20260427_150137.jpg",
    "size_bytes": 787560,
    "modified": "2026-04-27 15:01:43"
  },
  {
    "filename": "20260427_124435.jpg",
    "path": "/home/blueberry/code/my-window/20260427_124435.jpg",
    "size_bytes": 755234,
    "modified": "2026-04-27 12:44:42"
  },
  {
    "filename": "20260427_102727.jpg",
    "path": "/home/blueberry/code/my-window/20260427_102727.jpg",
    "size_bytes": 654258,
    "modified": "2026-04-27 10:27:34"
  },
  {
    "filename": "20260427_081007.jpg",
    "path": "/home/blueberry/code/my-window/20260427_081007.jpg",
    "size_bytes": 691978,
    "modified": "2026-04-27 08:10:13"
  },
  {
    "filename": "20260427_055304.jpg",
    "path": "/home/blueberry/code/my-window/20260427_055304.jpg",
    "size_bytes": 561981,
    "modified": "2026-04-27 05:53:11"
  },
  {
    "filename": "20260427_033557.jpg",
    "path": "/home/blueberry/code/my-window/20260427_033557.jpg",
    "size_bytes": 1295142,
    "modified": "2026-04-27 03:36:03"
  },
  {
    "filename": "20260427_011828.jpg",
    "path": "/home/blueberry/code/my-window/20260427_011828.jpg",
    "size_bytes": 1266546,
    "modified": "2026-04-27 01:18:35"
  },
  {
    "filename": "20260426_230107.jpg",
    "path": "/home/blueberry/code/my-window/20260426_230107.jpg",
    "size_bytes": 1267595,
    "modified": "2026-04-26 23:01:13"
  }
]
